bernhard_joe/pb.py
bernhard_joe/__init__.py
bernhard_joe-0.2.5.dist-info/METADATA
bernhard_joe-0.2.5.dist-info/DESCRIPTION.rst
bernhard_joe-0.2.5.dist-info/top_level.txt
bernhard_joe-0.2.5.dist-info/metadata.json
bernhard_joe-0.2.5.dist-info/RECORD
bernhard_joe-0.2.5.dist-info/WHEEL
